aider/__init__.py
aider/__main__.py
aider/analytics.py
aider/args.py
aider/args_formatter.py
aider/cli.py
aider/commands.py
aider/copypaste.py
aider/deprecated.py
aider/dump.py
aider/editor.py
aider/exceptions.py
aider/format_settings.py
aider/genius.py
aider/help.py
aider/help_pats.py
aider/history.py
aider/io.py
aider/jac_integration.py
aider/llm.py
aider/main.py
aider/mdstream.py
aider/models.py
aider/onboarding.py
aider/openrouter.py
aider/prompts.py
aider/repo.py
aider/report.py
aider/run_cmd.py
aider/scrape.py
aider/sendchat.py
aider/urls.py
aider/utils.py
aider/version.py
aider/versioncheck.py
aider/voice.py
aider/waiting.py
aider/watch.py
aider/coders/__init__.py
aider/coders/base_coder.py
aider/integration/__init__.py
aider/integration/file_editor.py
aider/integration/jac_bridge.py
aider/integration/llm_client.py
aider/integration/mtp_interface.py
aider/integration/osp_interface.py
aider/jac/__init__.py
aider/jac/architect_prompts.jac
aider/jac/change_coordinator.jac
aider/jac/context_gatherer.jac
aider/jac/editing_walker.jac
aider/jac/editor_prompts.jac
aider/jac/file_nodes.jac
aider/jac/genius_agent.jac
aider/jac/graph_walkers.jac
aider/jac/impact_analyzer.jac
aider/jac/mtp_prompts.jac
aider/jac/planning_walker.jac
aider/jac/ranking_algorithms.jac
aider/jac/repomap_osp.jac
aider/jac/spatial_graph.jac
aider/jac/token_optimizer.jac
aider/jac/tool_integration.jac
aider/jac/validation_walker.jac
aider/resources/__init__.py
aider/resources/model-settings.yml
aider_jac_osp-2.0.2.dist-info/METADATA
aider_jac_osp-2.0.2.dist-info/WHEEL
aider_jac_osp-2.0.2.dist-info/entry_points.txt
aider_jac_osp-2.0.2.dist-info/top_level.txt
aider_jac_osp-2.0.2.dist-info/RECORD
