Metadata-Version: 2.4
Name: aider-jac-osp
Version: 2.0.2
Summary: Aider: AI-powered coding assistant rebuilt with Jac Object-Spatial Programming and Genius Mode
Home-page: https://github.com/ThiruvarankanM/Rebuilding-Aider-with-Jac-OSP
Author: Thiruvarankan M
Author-email: thiru07official@gmail.com
Keywords: AI assistant LLM code OSP MTP Jac automation spatial-programming genius-mode
Classifier: Development Status :: 4 - Beta
Classifier: Programming Language :: Python :: 3
Classifier: Programming Language :: Python :: 3.8
Classifier: Programming Language :: Python :: 3.9
Classifier: Programming Language :: Python :: 3.10
Classifier: Programming Language :: Python :: 3.11
Classifier: Programming Language :: Python :: 3.12
Classifier: License :: OSI Approved :: Apache Software License
Classifier: Operating System :: OS Independent
Classifier: Intended Audience :: Developers
Classifier: Topic :: Software Development :: Code Generators
Classifier: Topic :: Scientific/Engineering :: Artificial Intelligence
Classifier: Topic :: Text Processing :: Linguistic
Requires-Python: >=3.8
Requires-Dist: rich>=13.5.0
Requires-Dist: prompt-toolkit>=3.0.0
Requires-Dist: configargparse>=1.7.0
Requires-Dist: pyperclip>=1.8.0
Requires-Dist: pillow>=9.0.0
Requires-Dist: litellm>=1.0.0
Requires-Dist: openai>=1.0.0
Requires-Dist: anthropic>=0.7.0
Requires-Dist: tiktoken>=0.7.0
Requires-Dist: tree-sitter>=0.20.0
Requires-Dist: gitpython>=3.1.0
Requires-Dist: aiofiles>=23.0.0
Requires-Dist: pydantic>=2.0.0
Requires-Dist: json5>=0.9.0
Requires-Dist: pyyaml>=6.0.0
Requires-Dist: shtab>=1.6.0
Requires-Dist: python-dotenv>=1.0.0
Provides-Extra: jac
Requires-Dist: jaclang>=0.7.0; extra == "jac"
Provides-Extra: dev
Requires-Dist: black>=24.0.0; extra == "dev"
Requires-Dist: isort>=5.12.0; extra == "dev"
Requires-Dist: flake8>=6.0.0; extra == "dev"
Requires-Dist: pytest>=7.0.0; extra == "dev"
Requires-Dist: pytest-mock>=3.10.0; extra == "dev"
Provides-Extra: demo
Requires-Dist: rich>=13.5.0; extra == "demo"
Dynamic: author
Dynamic: author-email
Dynamic: classifier
Dynamic: description
Dynamic: description-content-type
Dynamic: home-page
Dynamic: keywords
Dynamic: provides-extra
Dynamic: requires-dist
Dynamic: requires-python
Dynamic: summary
